[{"resource": {"umbrella": 0, "desk": 0, "water": 0, "pen": 0, "board": 0, "others": [], "chair": 0}, "resourceBody": [], "volunteerBody": ["Barron"], "county": "TPE-4", "poll": "tpe0337", "volunteer": 1}, {"resource": {"umbrella": 0, "desk": 0, "water": 0, "pen": 0, "board": 0, "others": [], "chair": 0}, "resourceBody": [], "volunteerBody": ["Cain"], "county": "TPE-4", "poll": "tpe0497", "volunteer": 1}, {"resource": {"umbrella": 0, "desk": 0, "water": 0, "pen": 0, "board": 0, "others": [], "chair": 0}, "resourceBody": [], "volunteerBody": ["\u9ec3\u6dd1\u5168"], "county": "TPE-4", "poll": "tpe0506", "volunteer": 1}, {"resource": {"umbrella": 0, "desk": 0, "water": 0, "pen": 0, "board": 0, "others": [], "chair": 0}, "resourceBody": [], "volunteerBody": ["Dalton"], "county": "TPE-4", "poll": "tpe0358", "volunteer": 1}, {"resource": {"umbrella": 0, "desk": 0, "water": 0, "pen": 0, "board": 0, "others": [], "chair": 0}, "resourceBody": [], "volunteerBody": ["McKenzie", "Walter"], "county": "TPE-4", "poll": "tpe0342", "volunteer": 2}, {"resource": {"umbrella": 0, "desk": 0, "water": 0, "pen": 0, "board": 0, "others": [], "chair": 0}, "resourceBody": [], "volunteerBody": ["Keller", "Dunn"], "county": "TPE-4", "poll": "tpe0355", "volunteer": 2}, {"resource": {"umbrella": 0, "desk": 0, "water": 0, "pen": 0, "board": 0, "others": [], "chair": 0}, "resourceBody": [], "volunteerBody": ["Davidson"], "county": "TPE-4", "poll": "tpe0466", "volunteer": 1}, {"resource": {"umbrella": 0, "desk": 0, "water": 0, "pen": 0, "board": 0, "others": [], "chair": 0}, "resourceBody": [], "volunteerBody": ["Barlow"], "county": "TPE-4", "poll": "tpe0338", "volunteer": 1}, {"resource": {"umbrella": 0, "desk": 0, "water": 5, "pen": 5, "board": 0, "others": [], "chair": 0}, "resourceBody": ["Porter"], "volunteerBody": [], "county": "TPE-4", "poll": "tpe0470", "volunteer": 0}, {"resource": {"umbrella": 0, "desk": 0, "water": 0, "pen": 0, "board": 0, "others": [], "chair": 0}, "resourceBody": [], "volunteerBody": ["Garrett"], "county": "TPE-4", "poll": "tpe0481", "volunteer": 1}, {"resource": {"umbrella": 0, "desk": 0, "water": 5, "pen": 5, "board": 0, "others": [], "chair": 0}, "resourceBody": ["\u674e\u63da\u60df"], "volunteerBody": ["\u9673\u706b\u822a", "Keith", "Mullen"], "county": "TPE-4", "poll": "tpe0515", "volunteer": 3}, {"resource": {"umbrella": 0, "desk": 0, "water": 0, "pen": 0, "board": 0, "others": [], "chair": 0}, "resourceBody": [], "volunteerBody": ["Hubbard", "Roberson", "Coleman", "\u674e\u63da\u60df"], "county": "TPE-4", "poll": "tpe0483", "volunteer": 4}, {"resource": {"umbrella": 0, "desk": 0, "water": 0, "pen": 0, "board": 0, "others": [], "chair": 0}, "resourceBody": [], "volunteerBody": ["Franklin", "McFadden", "Berg", "Sargent"], "county": "TPE-4", "poll": "tpe0499", "volunteer": 4}, {"resource": {"umbrella": 0, "desk": 0, "water": 0, "pen": 0, "board": 0, "others": [], "chair": 0}, "resourceBody": [], "volunteerBody": ["Whitaker"], "county": "TPE-4", "poll": "tpe0425", "volunteer": 1}, {"resource": {"umbrella": 0, "desk": 0, "water": 0, "pen": 10, "board": 0, "others": [], "chair": 0}, "resourceBody": ["Hodge"], "volunteerBody": ["Ford", "\u738b\u8a69\u5a77", "Moore", "Hayes", "\u5289\u548c\u65ed", "Phillips", "\u6797\u7d39\u606c"], "county": "TPE-4", "poll": "tpe0454", "volunteer": 7}, {"resource": {"umbrella": 0, "desk": 0, "water": 0, "pen": 15, "board": 0, "others": [], "chair": 0}, "resourceBody": ["Burt"], "volunteerBody": ["Shaffer", "Thompson", "Mullins"], "county": "TPE-4", "poll": "tpe0330", "volunteer": 3}, {"resource": {"umbrella": 0, "desk": 0, "water": 10, "pen": 10, "board": 10, "others": [], "chair": 0}, "resourceBody": ["Wiggins"], "volunteerBody": ["Owens", "\u5f35\u5f97\u7537", "Carpenter", "Young"], "county": "TPE-4", "poll": "tpe0378", "volunteer": 4}, {"resource": {"umbrella": 0, "desk": 0, "water": 0, "pen": 0, "board": 0, "others": [], "chair": 0}, "resourceBody": [], "volunteerBody": ["Scott"], "county": "TPE-4", "poll": "tpe0376", "volunteer": 1}, {"resource": {"umbrella": 0, "desk": 0, "water": 0, "pen": 0, "board": 0, "others": [], "chair": 0}, "resourceBody": [], "volunteerBody": ["\u674e\u63da\u60df", "Gardner", "Charles"], "county": "TPE-4", "poll": "tpe0516", "volunteer": 3}, {"resource": {"umbrella": 0, "desk": 0, "water": 0, "pen": 10, "board": 0, "others": [], "chair": 0}, "resourceBody": ["Rowland"], "volunteerBody": ["\u9673\u7407\u6c5f", "Bates"], "county": "TPE-4", "poll": "tpe0352", "volunteer": 2}, {"resource": {"umbrella": 0, "desk": 0, "water": 5, "pen": 0, "board": 0, "others": [], "chair": 0}, "resourceBody": ["Davidson"], "volunteerBody": ["Scott", "Park", "Armstrong"], "county": "TPE-4", "poll": "tpe0486", "volunteer": 3}, {"resource": {"umbrella": 0, "desk": 0, "water": 0, "pen": 0, "board": 0, "others": [], "chair": 0}, "resourceBody": [], "volunteerBody": ["Roberts", "\u8b1d\u653f\u9716", "Bray", "Curry"], "county": "TPE-4", "poll": "tpe0509", "volunteer": 4}, {"resource": {"umbrella": 0, "desk": 0, "water": 5, "pen": 5, "board": 0, "others": [], "chair": 2}, "resourceBody": ["Spears"], "volunteerBody": ["Glass", "\u9ec3\u6709\u4f69"], "county": "TPE-4", "poll": "tpe0398", "volunteer": 2}, {"resource": {"umbrella": 0, "desk": 0, "water": 0, "pen": 0, "board": 0, "others": [], "chair": 0}, "resourceBody": [], "volunteerBody": ["Nelson", "Parrish", "Harris", "\u8523\u6021\u5a77", "Wilson", "Levine", "\u5f35\u5176\u80b2", "Stephenson", "\u674e\u601d\u7a4e", "Armstrong"], "county": "TPE-4", "poll": "tpe0494", "volunteer": 10}, {"resource": {"umbrella": 0, "desk": 0, "water": 5, "pen": 5, "board": 0, "others": [], "chair": 0}, "resourceBody": ["McCoy"], "volunteerBody": ["Key", "Noble", "Baxter", "Burnett", "Maynard", "Boyd"], "county": "TPE-4", "poll": "tpe0423", "volunteer": 6}, {"resource": {"umbrella": 0, "desk": 0, "water": 10, "pen": 10, "board": 10, "others": [], "chair": 0}, "resourceBody": ["Ford", "Bowen"], "volunteerBody": ["McCarty", "Savage", "Larson", "Fuller", "Higgins"], "county": "TPE-4", "poll": "tpe0396", "volunteer": 5}, {"resource": {"umbrella": 0, "desk": 0, "water": 0, "pen": 0, "board": 0, "others": [], "chair": 0}, "resourceBody": [], "volunteerBody": ["Whitaker", "Ortiz", "Conrad"], "county": "TPE-4", "poll": "tpe0439", "volunteer": 3}, {"resource": {"umbrella": 0, "desk": 0, "water": 10, "pen": 10, "board": 5, "others": [], "chair": 0}, "resourceBody": ["Rivers", "\u5289\u96e8\u598d", "Skinner"], "volunteerBody": ["\u5f90\u6613\u7537", "Chase", "Stuart", "Weaver", "\u90ed\u667a\u5049"], "county": "TPE-4", "poll": "tpe0468", "volunteer": 5}, {"resource": {"umbrella": 0, "desk": 2, "water": 12, "pen": 10, "board": 2, "others": [], "chair": 4}, "resourceBody": ["Buckley", "Floyd"], "volunteerBody": ["Larsen", "Logan", "Koch"], "county": "TPE-4", "poll": "tpe0518", "volunteer": 3}, {"resource": {"umbrella": 0, "desk": 0, "water": 0, "pen": 0, "board": 0, "others": [], "chair": 0}, "resourceBody": [], "volunteerBody": ["Reilly", "\u6c88\u5609\u57ce", "Baldwin", "Christian"], "county": "TPE-4", "poll": "tpe0482", "volunteer": 4}, {"resource": {"umbrella": 0, "desk": 0, "water": 0, "pen": 0, "board": 0, "others": [], "chair": 0}, "resourceBody": [], "volunteerBody": ["Russell", "Sykes", "Mitchell", "Giles", "Mayer", "Christian"], "county": "TPE-4", "poll": "tpe0407", "volunteer": 6}, {"resource": {"umbrella": 0, "desk": 0, "water": 10, "pen": 10, "board": 0, "others": [], "chair": 0}, "resourceBody": ["\u674e\u7f8e\u82d3"], "volunteerBody": ["Montgomery", "Clay", "\u9673\u5be7\u9cf3", "\u5f35\u6021\u8431"], "county": "TPE-4", "poll": "tpe0360", "volunteer": 4}, {"resource": {"umbrella": 1, "desk": 1, "water": 5, "pen": 5, "board": 5, "others": [], "chair": 2}, "resourceBody": ["Lindsay", "Patton", "Levine"], "volunteerBody": ["Berger", "Gilmore", "Short"], "county": "TPE-4", "poll": "tpe0347", "volunteer": 3}, {"resource": {"umbrella": 0, "desk": 0, "water": 0, "pen": 5, "board": 0, "others": [], "chair": 0}, "resourceBody": ["Gilliam"], "volunteerBody": ["McDonald"], "county": "TPE-4", "poll": "tpe0402", "volunteer": 1}, {"resource": {"umbrella": 0, "desk": 0, "water": 5, "pen": 5, "board": 0, "others": [], "chair": 0}, "resourceBody": ["\u9673\u66f8\u5229"], "volunteerBody": ["Gross", "\u738b\u4f91\u9752", "Thompson", "Nelson", "Leon"], "county": "TPE-4", "poll": "tpe0336", "volunteer": 5}, {"resource": {"umbrella": 0, "desk": 0, "water": 5, "pen": 5, "board": 0, "others": [], "chair": 1}, "resourceBody": ["Johns", "\u912d\u5b87\u5176"], "volunteerBody": ["\u5289\u96e8\u598d", "Medina", "Walter", "\u8a31\u5b9b\u541b", "Snyder"], "county": "TPE-4", "poll": "tpe0493", "volunteer": 5}, {"resource": {"umbrella": 0, "desk": 0, "water": 0, "pen": 0, "board": 0, "others": [], "chair": 0}, "resourceBody": [], "volunteerBody": ["Gibson"], "county": "TPE-4", "poll": "tpe0348", "volunteer": 1}, {"resource": {"umbrella": 0, "desk": 0, "water": 5, "pen": 5, "board": 5, "others": [], "chair": 0}, "resourceBody": ["\u738b\u80b2\u83c1", "Watkins"], "volunteerBody": ["Sellers", "Cole", "Greene"], "county": "TPE-4", "poll": "tpe0350", "volunteer": 3}, {"resource": {"umbrella": 0, "desk": 0, "water": 0, "pen": 0, "board": 0, "others": [], "chair": 0}, "resourceBody": [], "volunteerBody": ["Giles", "Lucas", "Charles"], "county": "TPE-4", "poll": "tpe0356", "volunteer": 3}, {"resource": {"umbrella": 0, "desk": 0, "water": 1, "pen": 0, "board": 0, "others": [], "chair": 0}, "resourceBody": ["Baldwin"], "volunteerBody": ["\u6881\u59ff\u59a4", "Myers", "Holman", "Stevenson", "Duncan"], "county": "TPE-4", "poll": "tpe0384", "volunteer": 5}, {"resource": {"umbrella": 0, "desk": 0, "water": 10, "pen": 10, "board": 3, "others": [], "chair": 2}, "resourceBody": ["Christian", "\u9673\u91d1\u5ff5"], "volunteerBody": ["Powers", "\u5289\u9999\u7d0b", "Wilkins", "Black", "Richards", "Huffman", "Morrow", "Carey", "\u738b\u654f\u7407", "\u9ec3\u60e0\u5a77"], "county": "TPE-4", "poll": "tpe0332", "volunteer": 10}, {"resource": {"umbrella": 0, "desk": 0, "water": 5, "pen": 5, "board": 0, "others": [], "chair": 0}, "resourceBody": ["English"], "volunteerBody": ["Best", "Briggs", "Barr", "\u6797\u5805\u83f1"], "county": "TPE-4", "poll": "tpe0467", "volunteer": 4}, {"resource": {"umbrella": 0, "desk": 0, "water": 5, "pen": 5, "board": 0, "others": [], "chair": 0}, "resourceBody": ["Huff"], "volunteerBody": ["Mayer", "Potts", "Marshall"], "county": "TPE-4", "poll": "tpe0498", "volunteer": 3}, {"resource": {"umbrella": 0, "desk": 0, "water": 35, "pen": 35, "board": 0, "others": [], "chair": 2}, "resourceBody": ["Calderon", "\u99ae\u6587\u5091", "Walter"], "volunteerBody": ["Hamilton", "Britt", "Beck", "Dillard", "\u502a\u4e2d\u923a", "Pearson", "Kirkland", "Mack", "Parsons"], "county": "TPE-4", "poll": "tpe0432", "volunteer": 9}, {"resource": {"umbrella": 0, "desk": 0, "water": 0, "pen": 0, "board": 0, "others": [], "chair": 0}, "resourceBody": [], "volunteerBody": ["West", "\u6bdb\u541f\u6167", "Goodwin"], "county": "TPE-4", "poll": "tpe0343", "volunteer": 3}, {"resource": {"umbrella": 0, "desk": 0, "water": 15, "pen": 15, "board": 15, "others": [], "chair": 0}, "resourceBody": ["Good", "Duran", "Dalton"], "volunteerBody": ["Richmond", "\u9ec3\u96e8\u5a1f", "McGee", "Shepard", "Dixon", "\u738b\u667a\u582f", "\u5f35\u96c5\u742a", "Wells"], "county": "TPE-4", "poll": "tpe0399", "volunteer": 8}, {"resource": {"umbrella": 0, "desk": 0, "water": 5, "pen": 5, "board": 5, "others": [], "chair": 0}, "resourceBody": ["McLeod"], "volunteerBody": ["Johnson", "Battle", "Mullins", "Lucas", "Weaver"], "county": "TPE-4", "poll": "tpe0490", "volunteer": 5}, {"resource": {"umbrella": 0, "desk": 0, "water": 55, "pen": 60, "board": 0, "others": [], "chair": 0}, "resourceBody": ["Strickland", "\u8521\u5fd7\u83ef", "Wood"], "volunteerBody": ["Carlson", "\u674e\u5a49\u541b", "Grimes", "Lambert", "Stanton", "Charles", "Hurley", "Clarke", "\u66fe\u5029\u5bcc", "Mueller", "Howe", "Frost", "Jordan", "\u5f35\u81f4\u8ecd", "Andrews", "Sims"], "county": "TPE-4", "poll": "tpe0381", "volunteer": 16}, {"resource": {"umbrella": 2, "desk": 1, "water": 5, "pen": 5, "board": 5, "others": [], "chair": 7}, "resourceBody": ["McKenzie", "Ortega", "Jacobson", "Farrell"], "volunteerBody": ["\u5f35\u4e39\u4e1e", "\u738b\u97fb\u4fe1", "Waller"], "county": "TPE-4", "poll": "tpe0424", "volunteer": 3}, {"resource": {"umbrella": 0, "desk": 0, "water": 25, "pen": 25, "board": 10, "others": [], "chair": 5}, "resourceBody": ["Booker", "Pratt", "Bowman"], "volunteerBody": ["Skinner", "\u5f35\u6770\u5149", "Talley", "McConnell", "Bowman", "Harmon", "Freeman", "Black", "Mitchell", "Small", "McGuire", "Hodges", "Davenport", "\u8a31\u975c\u5b9c", "Herring"], "county": "TPE-4", "poll": "tpe0319", "volunteer": 15}, {"resource": {"umbrella": 0, "desk": 0, "water": 0, "pen": 25, "board": 5, "others": [], "chair": 1}, "resourceBody": ["Bennett"], "volunteerBody": ["Olsen", "\u6797\u4f69\u4ea8", "McFadden", "Chambers", "Alford", "O'Connor", "\u8523\u6021\u5a77", "Rowland"], "county": "TPE-4", "poll": "tpe0340", "volunteer": 8}, {"resource": {"umbrella": 0, "desk": 0, "water": 15, "pen": 30, "board": 15, "others": [], "chair": 6}, "resourceBody": ["Rowland", "Shields", "Roy", "Clements", "\u9ec3\u6b23\u5b9c", "Spence"], "volunteerBody": ["Graham", "Lowe", "Cherry", "Bird", "Maddox", "Gallagher", "\u9127\u653f\u5112", "Gilbert", "Combs", "Faulkner", "Larsen", "Townsend", "Gallegos", "Watts", "Walsh"], "county": "TPE-4", "poll": "tpe0413", "volunteer": 15}, {"resource": {"umbrella": 0, "desk": 0, "water": 30, "pen": 30, "board": 0, "others": [], "chair": 0}, "resourceBody": ["Hardy"], "volunteerBody": ["Parsons", "Reyes", "\u8449\u8587\u5091", "\u9ec3\u6709\u4f69", "Lara", "Walsh", "Watkins"], "county": "TPE-4", "poll": "tpe0477", "volunteer": 7}, {"resource": {"umbrella": 0, "desk": 0, "water": 5, "pen": 5, "board": 0, "others": [], "chair": 0}, "resourceBody": ["Stein"], "volunteerBody": ["Reed", "\u674e\u5b97\u8302"], "county": "TPE-4", "poll": "tpe0335", "volunteer": 2}, {"resource": {"umbrella": 0, "desk": 0, "water": 5, "pen": 5, "board": 0, "others": [], "chair": 0}, "resourceBody": ["Merrill"], "volunteerBody": ["Thomas", "Austin", "Walsh", "Nicholson", "\u6797\u5805\u83f1"], "county": "TPE-4", "poll": "tpe0504", "volunteer": 5}, {"resource": {"umbrella": 0, "desk": 1, "water": 2, "pen": 14, "board": 3, "others": [], "chair": 4}, "resourceBody": ["\u5289\u6b23\u6021", "Dickerson", "Pope", "Booth"], "volunteerBody": ["Fox", "Daugherty", "Brooks", "\u6797\u7d39\u606c", "\u8b1d\u5c0f\u96c4", "Baxter", "Nixon", "\u6797\u6dd1\u5982", "\u5f90\u6613\u7537", "McGowan", "Duncan", "McKnight"], "county": "TPE-4", "poll": "tpe0312", "volunteer": 12}, {"resource": {"umbrella": 0, "desk": 3, "water": 25, "pen": 25, "board": 0, "others": [], "chair": 4}, "resourceBody": ["Christian", "McCray"], "volunteerBody": ["\u6797\u6021\u81fb", "Hoffman", "Tate", "Sanford", "\u738b\u6631\u5764", "\u8a31\u5b9b\u541b", "Shaffer", "Holt", "McDaniel", "Good", "Green", "Frye", "Wilkins", "Montgomery", "\u5433\u653f\u884c", "\u9673\u6587\u5f6c", "Gregory", "\u674e\u5a49\u541b"], "county": "TPE-4", "poll": "tpe0322", "volunteer": 18}, {"resource": {"umbrella": 0, "desk": 0, "water": 5, "pen": 10, "board": 0, "others": [], "chair": 0}, "resourceBody": ["O'Neil", "\u90ed\u667a\u5049", "\u694a\u60e0\u96ef"], "volunteerBody": ["Haley", "Erickson", "Bryant", "\u6881\u6db5\u5bb9", "Coleman", "\u6797\u6021\u81fb", "\u9673\u6587\u5b8f", "Kelly", "\u674e\u7f8e\u82d3", "Malone"], "county": "TPE-4", "poll": "tpe0500", "volunteer": 10}, {"resource": {"umbrella": 0, "desk": 0, "water": 10, "pen": 10, "board": 2, "others": [], "chair": 0}, "resourceBody": ["\u674e\u63da\u60df", "Hester"], "volunteerBody": ["Griffith", "Britt", "Hoffman", "\u9ec3\u4fca\u7fbd", "\u8861\u6dd1\u654f", "Branch", "Hardy", "Pickett", "\u6797\u6021\u81fb", "Pierce", "\u9673\u6176\u6607", "Norton"], "county": "TPE-4", "poll": "tpe0317", "volunteer": 12}, {"resource": {"umbrella": 0, "desk": 0, "water": 10, "pen": 10, "board": 0, "others": [], "chair": 0}, "resourceBody": ["Barron", "Horne"], "volunteerBody": ["Sims", "\u738b\u6631\u5764", "McNeil", "Kelley", "Stokes", "\u7f85\u6620\u5c4f", "Donaldson", "Olson", "Jacobson", "Hammond"], "county": "TPE-4", "poll": "tpe0364", "volunteer": 10}, {"resource": {"umbrella": 0, "desk": 0, "water": 20, "pen": 20, "board": 0, "others": [], "chair": 0}, "resourceBody": ["Hoffman"], "volunteerBody": ["Hooper", "\u8b1d\u4e16\u4eae", "Hancock", "Luna", "\u6797\u4fca\u5b8f", "Holmes", "English", "Serrano", "Buck", "Chapman", "Vaughan"], "county": "TPE-4", "poll": "tpe0507", "volunteer": 11}, {"resource": {"umbrella": 0, "desk": 1, "water": 25, "pen": 25, "board": 10, "others": [], "chair": 5}, "resourceBody": ["Perry", "Collins", "Cohen"], "volunteerBody": ["\u8b1d\u80b2\u5112", "Sparks", "Young", "Ray", "Johnson", "McBride", "\u9673\u5be7\u9cf3"], "county": "TPE-4", "poll": "tpe0391", "volunteer": 7}, {"resource": {"umbrella": 0, "desk": 0, "water": 1, "pen": 1, "board": 1, "others": [], "chair": 0}, "resourceBody": ["Hamilton", "Key"], "volunteerBody": ["\u9ec3\u5927\u5c39", "Lambert", "Rose", "Rodgers", "McFarland"], "county": "TPE-4", "poll": "tpe0491", "volunteer": 5}, {"resource": {"umbrella": 0, "desk": 1, "water": 5, "pen": 5, "board": 5, "others": [], "chair": 2}, "resourceBody": ["Carey"], "volunteerBody": ["\u5289\u4fca\u7407", "\u5289\u4fca\u5947", "\u99ae\u6587\u5091", "\u8a79\u96c5\u5ba3"], "county": "TPE-4", "poll": "tpe0403", "volunteer": 4}, {"resource": {"umbrella": 0, "desk": 0, "water": 15, "pen": 15, "board": 0, "others": [], "chair": 0}, "resourceBody": ["Rowland"], "volunteerBody": ["Rivers", "Reyes", "\u8881\u4fca\u69ae", "\u7c21\u5fd7\u96c4", "Berry", "\u80e1\u6c9b\u99ff", "Cain", "\u8521\u5b5f\u9054", "Hayes", "Daniel", "Prince", "Hines", "Burton", "Weber", "Ellis", "Lyons"], "county": "TPE-4", "poll": "tpe0510", "volunteer": 16}, {"resource": {"umbrella": 1, "desk": 1, "water": 5, "pen": 5, "board": 1, "others": [], "chair": 2}, "resourceBody": ["Davis", "Melton", "Bridges"], "volunteerBody": ["Moran", "Newman", "Stevens", "Lynch", "Kirkland"], "county": "TPE-4", "poll": "tpe0327", "volunteer": 5}, {"resource": {"umbrella": 0, "desk": 0, "water": 0, "pen": 30, "board": 30, "others": [], "chair": 7}, "resourceBody": ["\u5201\u5049\u6210", "Frederick", "Oliver"], "volunteerBody": ["\u912d\u5b87\u5176", "Reese", "Wilkerson", "Irwin", "Jordan", "Terrell", "McPherson", "Hatfield", "Ballard", "\u5f35\u7d20\u8c9e"], "county": "TPE-4", "poll": "tpe0463", "volunteer": 10}, {"resource": {"umbrella": 1, "desk": 0, "water": 10, "pen": 40, "board": 1, "others": [], "chair": 1}, "resourceBody": ["Stout", "Madden", "Lester"], "volunteerBody": ["Hodge", "Kidd", "Wright", "Erickson", "\u912d\u5b87\u5176", "Grimes", "Fisher", "Bright", "\u5f35\u5176\u80b2", "Perry", "Beach", "Sims", "Pace", "\u8861\u6dd1\u654f", "Tyson", "Melton", "Herring", "Martin", "Hunt", "Luna", "Holland", "Osborne"], "county": "TPE-4", "poll": "tpe0409", "volunteer": 22}, {"resource": {"umbrella": 0, "desk": 0, "water": 5, "pen": 5, "board": 0, "others": [], "chair": 0}, "resourceBody": ["\u694a\u60e0\u96ef", "Knight", "Mooney"], "volunteerBody": ["Swanson", "\u5f35\u7d20\u8c9e", "\u5f35\u6021\u8431", "Reyes", "Collier", "Kramer", "\u8449\u7389\u73b2", "Stephens", "Park", "Mason"], "county": "TPE-4", "poll": "tpe0316", "volunteer": 10}, {"resource": {"umbrella": 4, "desk": 4, "water": 20, "pen": 20, "board": 20, "others": [], "chair": 8}, "resourceBody": ["\u9673\u7f8e\u5f18", "\u694a\u660e\u7ff0"], "volunteerBody": ["\u8b1d\u4e16\u4eae", "Haley", "Miles", "Walter", "Justice", "Ford", "Tyson", "Cain", "O'Neill", "\u9ec3\u4fca\u7fbd", "Kidd"], "county": "TPE-4", "poll": "tpe0456", "volunteer": 10}, {"resource": {"umbrella": 0, "desk": 0, "water": 10, "pen": 10, "board": 0, "others": [], "chair": 0}, "resourceBody": ["Humphrey", "Crane"], "volunteerBody": ["Craft", "\u7c21\u5fd7\u96c4", "David", "King"], "county": "TPE-4", "poll": "tpe0370", "volunteer": 4}, {"resource": {"umbrella": 0, "desk": 0, "water": 10, "pen": 10, "board": 0, "others": [], "chair": 0}, "resourceBody": ["Sanders"], "volunteerBody": ["House", "Hatfield", "Anderson", "Larson", "\u55bb\u8ce2\u65b9", "Watkins", "Britt", "Rivera", "Stevens"], "county": "TPE-4", "poll": "tpe0372", "volunteer": 9}, {"resource": {"umbrella": 0, "desk": 0, "water": 5, "pen": 5, "board": 0, "others": [], "chair": 0}, "resourceBody": ["Bruce"], "volunteerBody": ["\u9ec3\u51f1\u97cb", "Shannon"], "county": "TPE-4", "poll": "tpe0354", "volunteer": 2}, {"resource": {"umbrella": 5, "desk": 0, "water": 25, "pen": 25, "board": 5, "others": [], "chair": 2}, "resourceBody": ["Colon", "\u9673\u54c1\u752b", "Farley", "Sargent"], "volunteerBody": ["\u502a\u5927\u5947", "Hurst", "Hawkins", "Rogers", "Bernard", "Jackson", "\u9ec3\u81f4\u9060", "Hardy", "Reid", "Wright", "Dillon", "\u8449\u7389\u73b2", "Stout"], "county": "TPE-4", "poll": "tpe0426", "volunteer": 13}, {"resource": {"umbrella": 0, "desk": 0, "water": 5, "pen": 5, "board": 5, "others": [], "chair": 2}, "resourceBody": ["Durham"], "volunteerBody": ["Bruce", "Good"], "county": "TPE-4", "poll": "tpe0431", "volunteer": 2}, {"resource": {"umbrella": 0, "desk": 0, "water": 5, "pen": 5, "board": 5, "others": [], "chair": 2}, "resourceBody": ["Hatfield", "Donovan"], "volunteerBody": ["Day", "Booth", "Heath", "\u6c88\u6d69\u6c11", "\u85cd\u65b0\u6797"], "county": "TPE-4", "poll": "tpe0505", "volunteer": 5}, {"resource": {"umbrella": 0, "desk": 1, "water": 0, "pen": 5, "board": 0, "others": [], "chair": 2}, "resourceBody": ["Booker"], "volunteerBody": ["Finch", "Howard", "Decker", "Duke", "Rogers"], "county": "TPE-4", "poll": "tpe0492", "volunteer": 5}, {"resource": {"umbrella": 2, "desk": 2, "water": 20, "pen": 20, "board": 10, "others": [], "chair": 4}, "resourceBody": ["Holloway", "Lowery", "Maddox", "Berg"], "volunteerBody": ["\u912d\u742a\u653f", "Clements", "O'Donnell", "McIntyre", "\u90b1\u6021\u5fd7", "Vincent", "Swanson", "Manning", "Hale", "Nelson", "Black", "\u9ec3\u6709\u4f69", "Joyce"], "county": "TPE-4", "poll": "tpe0303", "volunteer": 13}, {"resource": {"umbrella": 0, "desk": 0, "water": 20, "pen": 0, "board": 0, "others": [], "chair": 0}, "resourceBody": ["Wilcox", "\u8b1d\u4f69\u6885"], "volunteerBody": ["Small", "Shaffer", "Mays", "Riddle", "Cline", "Burke", "Murphy", "Campbell", "\u5f35\u96c5\u742a", "\u9127\u653f\u5112", "Carson", "O'Donnell", "Dotson"], "county": "TPE-4", "poll": "tpe0450", "volunteer": 13}, {"resource": {"umbrella": 0, "desk": 0, "water": 30, "pen": 30, "board": 30, "others": [], "chair": 12}, "resourceBody": ["Dunn", "Watson", "O'Donnell", "Jensen"], "volunteerBody": ["\u55bb\u8ce2\u65b9", "Pittman", "West", "Cooke", "\u5289\u96e8\u598d", "Reyes", "\u6797\u6f54\u8283", "Kirkland", "Terry", "Mays", "\u9ec3\u5f65\u5747", "\u8861\u6dd1\u654f", "\u9673\u5bb6\u677e", "Shaw", "\u8881\u4fca\u69ae"], "county": "TPE-4", "poll": "tpe0344", "volunteer": 15}, {"resource": {"umbrella": 0, "desk": 3, "water": 15, "pen": 15, "board": 3, "others": [], "chair": 6}, "resourceBody": ["Mann", "Randolph", "Gentry"], "volunteerBody": ["Lindsey", "O'Neill", "Hewitt", "Stein", "Thompson", "Garner", "Chambers", "McCarthy", "Farley", "Callahan", "\u9127\u653f\u5112"], "county": "TPE-4", "poll": "tpe0487", "volunteer": 11}, {"resource": {"umbrella": 0, "desk": 0, "water": 15, "pen": 15, "board": 16, "others": [], "chair": 2}, "resourceBody": ["Green", "\u5b8b\u5a01\u5357", "Barber", "Young", "\u674e\u5a49\u541b"], "volunteerBody": ["Beck", "Wade", "Whitaker", "Marshall", "Carney", "\u738b\u8a69\u5a77", "Haynes", "Barron", "Riley", "French", "Bush", "Sims", "Michael", "Erickson", "Hamilton", "Wheeler"], "county": "TPE-4", "poll": "tpe0307", "volunteer": 16}, {"resource": {"umbrella": 0, "desk": 0, "water": 20, "pen": 20, "board": 0, "others": [], "chair": 0}, "resourceBody": ["Waters", "Levine"], "volunteerBody": ["Rodgers", "Lynn", "Cleveland", "Peters", "Maddox", "Stein", "\u502a\u5927\u5947", "Dunn", "\u674e\u6021\u5a77", "Price", "Potts", "Howard", "Hester", "\u502a\u5927\u5947", "Barron", "McCullough", "Bright", "Gilliam", "Blevins", "Stevens"], "county": "TPE-4", "poll": "tpe0305", "volunteer": 20}, {"resource": {"umbrella": 0, "desk": 0, "water": 20, "pen": 20, "board": 20, "others": [], "chair": 0}, "resourceBody": ["\u9f8d\u5b89\u742a", "Case"], "volunteerBody": ["Rowe", "\u8449\u8587\u5091", "Roberts", "Lang", "McLean", "Randolph", "\u5f35\u6770\u5149", "\u6797\u5100\u73e0", "\u5289\u5fd7\u5029", "Crosby"], "county": "TPE-4", "poll": "tpe0472", "volunteer": 10}, {"resource": {"umbrella": 0, "desk": 0, "water": 15, "pen": 15, "board": 15, "others": [], "chair": 0}, "resourceBody": ["\u8b1d\u653f\u9716", "Frazier"], "volunteerBody": ["\u674e\u5b97\u8302", "Ferrell", "O'Brien", "Roy", "Rowland", "\u6797\u4f69\u4ea8", "Emerson", "Knowles", "Harper", "\u694a\u660e\u7ff0", "Sampson", "Mueller"], "county": "TPE-4", "poll": "tpe0460", "volunteer": 12}, {"resource": {"umbrella": 0, "desk": 0, "water": 30, "pen": 30, "board": 0, "others": [], "chair": 0}, "resourceBody": ["Terry"], "volunteerBody": ["Quinn", "Rowe", "Adams", "Baker", "Christensen", "Harrell", "Frazier", "\u90b1\u6021\u5fd7", "\u5f90\u6613\u7537", "\u5f35\u54f2\u6607"], "county": "TPE-4", "poll": "tpe0366", "volunteer": 10}, {"resource": {"umbrella": 0, "desk": 0, "water": 0, "pen": 0, "board": 0, "others": [], "chair": 0}, "resourceBody": [], "volunteerBody": ["Aguirre", "Walters", "Cooper"], "county": "TPE-4", "poll": "tpe0380", "volunteer": 3}, {"resource": {"umbrella": 0, "desk": 0, "water": 5, "pen": 5, "board": 0, "others": [], "chair": 4}, "resourceBody": ["English", "Pace", "Horn"], "volunteerBody": ["Bright", "Sharp", "Lindsey", "Grimes"], "county": "TPE-4", "poll": "tpe0377", "volunteer": 4}]
